{
  "DefaultProjectDescription": "Update Process With Approval (Clone-Build-Publish-Update-Approve-Download-Publish-Update)",
  "DefaultProjectName": "UpdateProcessWithApproval",
  "Dependencies": {
    "UiPath.Persistence.Activities": "[1.4.1]",
    "UiPath.Pipelines.Activities": "[1.0.0-preview]",
    "UiPath.System.Activities": "[22.10.2]",
    "UiPath.WebAPI.Activities": "[1.13.2]"
  },
  "Description": "Update Process With Approval Pipeline Template\r\n(Clone-Build-Publish-Update-Approve-Download-Publish-Update)",
  "DisplayPriority": 0,
  "ExceptionHandlerWorkflow": null,
  "IconUri": "CustomProcessCSharpIcon",
  "IsBlank": false,
  "Label": "Process",
  "MainFile": "Main.xaml",
  "EntryPoints": [
    {
      "FilePath": "Main.xaml",
      "UniqueId": "eeb57af1-61d1-4cb5-82b3-0467fd6613a0",
      "IsPrivate": null,
      "Input": [],
      "Output": []
    }
  ],
  "EntitiesStores": [],
  "Name": "UpdateProcessWithApprovalPipelineTemplate",
  "NewTemplateTitle": null,
  "PrivateFiles": [],
  "OutputType": 0,
  "ProjectProfile": 0,
  "ExpressionLanguage": 1,
  "TargetFramework": 2,
  "SupportsPersistence": true,
  "ModernBehavior": true,
  "RequiresUserInteraction": false,
  "ReadyForPiP": false,
  "StartsInPiP": false,
  "IsPausable": true,
  "IsAttended": false,
  "IsLocalized": false,
  "PackageIconUrl": null,
  "AutoDispose": false,
  "FileInfoCollection": []
}