{
  "DefaultProjectDescription": "NewOrchestrationProcessDefaultDescription",
  "DefaultProjectName": "NewOrchestrationProcessDefaultName",
  "Dependencies": {
    "UiPath.Excel.Activities": "[2.16.0]",
    "UiPath.FormActivityLibrary": "[1.7.1]",
    "UiPath.Persistence.Activities": "[1.4.0]",
    "UiPath.System.Activities": "[22.10.3]"
  },
  "Description": "NewOrchestrationProcessDescription",
  "DisplayPriority": 1,
  "ExceptionHandlerWorkflow": null,
  "IconUri": "OrchestrationProcessTemplateIcon",
  "IsBlank": false,
  "Label": "NewOrchestrationProcessTemplateLabel",
  "MainFile": "Main.xaml",
  "Name": "NewOrchestrationProcessTemplateTitle",
  "NewTemplateTitle": "NewOrchestrationProcessNewTemplateTitle",
  "PrivateFiles": null,
  "ProjectProfile": "Developement",
  "OutputType": "Process",
  "ExpressionLanguage": "CSharp",
  "SupportsPersistence": true,
  "RequiresUserInteraction": false,
  "TargetFramework": "Legacy",
  "IsLocalized": true
}