{
  "DefaultProjectDescription": "DownloadFileDefaultDescription",
  "DefaultProjectName": "DownloadFileDefaultName",
  "Dependencies": {
    "UiPath.ComplexScenarios.Activities": "[1.2.0-preview]",
    "UiPath.Excel.Activities": "[2.13.0-preview]",
    "UiPath.Mail.Activities": "[1.16.0-preview]",
    "UiPath.Presentations.Activities": "[1.4.0-preview]",
    "UiPath.System.Activities": "[22.7.0-preview]",
    "UiPath.UIAutomation.Activities": "[22.7.0-preview]",
    "UiPath.Word.Activities": "[1.11.0-preview]"
  },
  "Description": "DownloadFileDescription",
  "DisplayPriority": 0,
  "ExceptionHandlerWorkflow": "GlobalHandlerX.xaml",
  "IconUri": "BusinessProjectTemplateIcon",
  "IsBlank": false,
  "Label": "DownloadFileLabel",
  "MainFile": "Main.xaml",
  "Name": "DownloadFileTemplateTitle",
  "NewTemplateTitle": "DownloadFileNewTemplateTitle",
  "PrivateFiles": null,
  "ProjectProfile": "Business",
  "OutputType": "Process",
  "AutoDispose": false,
  "IsLocalized": true
}