{
  "DefaultProjectDescription": "Clone the solution projects code - Analyze - Run Tests - Build - Publish packages - Update processes - Re-sync solution - Create solution package - Deploy solution - Approve - Download solution package - Upload solution package to next environment - Deploy solution to next environment.\n\r\n\rRead more in Automation Ops - Pipelines documentation.",
  "DefaultProjectName": "Solution Deployment Pipeline",
  "Dependencies": {
    "UiPath.FormActivityLibrary": "[2.0.8]",
    "UiPath.Persistence.Activities": "[1.5.11]",
    "UiPath.Pipelines.Activities": "[2.1.0-preview]",
    "UiPath.System.Activities": "[23.10.6]",
    "UiPath.Testing.Activities": "[23.10.1]",
    "UiPath.WebAPI.Activities": "[1.18.0]"
  },
  "Description": "Clone the solution projects code - Analyze - Run Tests - Build - Publish packages - Update processes - Re-sync solution - Create solution package - Deploy solution - Approve - Download solution package - Upload solution package to next environment - Deploy solution to next environment.\n\r\n\rRead more in Automation Ops - Pipelines documentation.",
  "DisplayPriority": 0,
  "ExceptionHandlerWorkflow": null,
  "IconUri": "CustomProcessVBIcon",
  "IsBlank": false,
  "Label": "Process",
  "MainFile": "Main.xaml",
  "EntryPoints": [
    {
      "FilePath": "Main.xaml",
      "UniqueId": "85b2fd5f-ecdf-4e3f-947b-448e30fdaadb",
      "IsPrivate": null,
      "Input": [],
      "Output": []
    }
  ],
  "EntitiesStores": [],
  "Name": "Solution Deployment Pipeline",
  "NewTemplateTitle": null,
  "PrivateFiles": [],
  "OutputType": 0,
  "ProjectProfile": 0,
  "ExpressionLanguage": 0,
  "TargetFramework": 2,
  "SupportsPersistence": true,
  "ModernBehavior": true,
  "RequiresUserInteraction": false,
  "PipType": 0,
  "ReadyForPiP": false,
  "StartsInPiP": false,
  "IsPausable": true,
  "IsAttended": false,
  "IsLocalized": false,
  "PackageIconUrl": null,
  "AutoDispose": false,
  "FileInfoCollection": [
    {
      "editingStatus": "InProgress",
      "testCaseId": "b6e9b0de-dad6-4be4-a54f-14adc6ea3049",
      "testCaseType": "TestCase",
      "executionTemplateInvokeIsolated": false,
      "fileName": "TestCase.xaml"
    }
  ]
}