{"api_version": "1.2", "fields": {"billing-addr": {"boxes": [{"boundingPoly": {"vertices": [{"x": 98, "y": 264}, {"x": 108, "y": 264}, {"x": 108, "y": 277}, {"x": 98, "y": 277}]}, "description": "2", "doc_line": 5, "line": 5, "page": 0}, {"boundingPoly": {"vertices": [{"x": 109, "y": 264}, {"x": 142, "y": 264}, {"x": 142, "y": 277}, {"x": 109, "y": 277}]}, "description": "Court", "doc_line": 5, "line": 5, "page": 0}, {"boundingPoly": {"vertices": [{"x": 143, "y": 264}, {"x": 186, "y": 264}, {"x": 186, "y": 279}, {"x": 143, "y": 279}]}, "description": "Square", "doc_line": 5, "line": 5, "page": 0}, {"boundingPoly": {"vertices": [{"x": 99, "y": 282}, {"x": 126, "y": 282}, {"x": 126, "y": 295}, {"x": 99, "y": 295}]}, "description": "New", "doc_line": 7, "line": 7, "page": 0}, {"boundingPoly": {"vertices": [{"x": 127, "y": 282}, {"x": 158, "y": 282}, {"x": 158, "y": 297}, {"x": 127, "y": 297}]}, "description": "York,", "doc_line": 7, "line": 7, "page": 0}, {"boundingPoly": {"vertices": [{"x": 160, "y": 282}, {"x": 180, "y": 282}, {"x": 180, "y": 295}, {"x": 160, "y": 295}]}, "description": "NY", "doc_line": 7, "line": 7, "page": 0}, {"boundingPoly": {"vertices": [{"x": 181, "y": 282}, {"x": 218, "y": 282}, {"x": 218, "y": 295}, {"x": 181, "y": 295}]}, "description": "12210", "doc_line": 7, "line": 7, "page": 0}], "confidence": 0.7819544076919556, "page": 0, "value": "2 Court Square New York, NY 12210", "value_raw": "2 Court Square New York, NY 12210"}, "billing-name": {"boxes": [{"boundingPoly": {"vertices": [{"x": 97, "y": 246}, {"x": 128, "y": 246}, {"x": 128, "y": 259}, {"x": 97, "y": 259}]}, "description": "John", "doc_line": 4, "line": 4, "page": 0}, {"boundingPoly": {"vertices": [{"x": 130, "y": 246}, {"x": 163, "y": 246}, {"x": 163, "y": 259}, {"x": 130, "y": 259}]}, "description": "Smith", "doc_line": 4, "line": 4, "page": 0}], "confidence": 0.8436598777770996, "page": 0, "value": "John Smith", "value_raw": "John Smith"}, "billing-vat-no": {"boxes": [], "confidence": 0.0, "page": 0, "value": "", "value_raw": ""}, "currency": {"confidence": 0.9922136664390564, "value": "USD"}, "date": {"boxes": [{"boundingPoly": {"vertices": [{"x": 632, "y": 219}, {"x": 697, "y": 219}, {"x": 697, "y": 231}, {"x": 632, "y": 231}]}, "description": "11/02/2019", "doc_line": 3, "line": 3, "page": 0}], "confidence": 0.946897029876709, "page": 0, "value": "2019-02-11", "value_raw": "11/02/2019"}, "discount": {"boxes": [], "confidence": 0.0, "page": 0, "value": "", "value_raw": ""}, "due-date": {"boxes": [{"boundingPoly": {"vertices": [{"x": 631, "y": 273}, {"x": 697, "y": 273}, {"x": 697, "y": 286}, {"x": 631, "y": 286}]}, "description": "26/02/2019", "doc_line": 6, "line": 6, "page": 0}], "confidence": 0.9519150853157043, "page": 0, "value": "2019-02-26", "value_raw": "26/02/2019"}, "invoice-no": {"boxes": [], "confidence": 0.0, "page": 0, "value": "", "value_raw": ""}, "items": [{"description": {"boxes": [{"boundingPoly": {"vertices": [{"x": 165, "y": 381}, {"x": 197, "y": 381}, {"x": 197, "y": 394}, {"x": 165, "y": 394}]}, "description": "Front", "doc_line": 9, "line": 9, "page": 0}, {"boundingPoly": {"vertices": [{"x": 198, "y": 382}, {"x": 220, "y": 382}, {"x": 220, "y": 394}, {"x": 198, "y": 394}]}, "description": "and", "doc_line": 9, "line": 9, "page": 0}, {"boundingPoly": {"vertices": [{"x": 222, "y": 383}, {"x": 247, "y": 383}, {"x": 247, "y": 394}, {"x": 222, "y": 394}]}, "description": "rear", "doc_line": 9, "line": 9, "page": 0}, {"boundingPoly": {"vertices": [{"x": 248, "y": 381}, {"x": 281, "y": 381}, {"x": 281, "y": 393}, {"x": 248, "y": 393}]}, "description": "brake", "doc_line": 9, "line": 9, "page": 0}, {"boundingPoly": {"vertices": [{"x": 283, "y": 381}, {"x": 321, "y": 381}, {"x": 321, "y": 394}, {"x": 283, "y": 394}]}, "description": "cables", "doc_line": 9, "line": 9, "page": 0}], "confidence": 0.9609047174453735, "page": 0, "value": "Front and rear brake cables", "value_raw": "Front and rear brake cables"}, "item-po-no": {"boxes": [], "confidence": 0.0, "page": 0, "value": "", "value_raw": ""}, "line-amount": {"boxes": [{"boundingPoly": {"vertices": [{"x": 649, "y": 381}, {"x": 690, "y": 381}, {"x": 690, "y": 394}, {"x": 649, "y": 394}]}, "description": "100.00", "doc_line": 9, "line": 9, "page": 0}], "confidence": 0.9756807088851929, "page": 0, "value": "100.00", "value_raw": "100.00"}, "line-no": {"boxes": [], "confidence": 0.0, "page": 0, "value": "", "value_raw": ""}, "part-no": {"boxes": [], "confidence": 0.0, "page": 0, "value": "", "value_raw": ""}, "quantity": {"boxes": [{"boundingPoly": {"vertices": [{"x": 107, "y": 381}, {"x": 114, "y": 381}, {"x": 114, "y": 393}, {"x": 107, "y": 393}]}, "description": "1", "doc_line": 9, "line": 9, "page": 0}], "confidence": 0.8049509525299072, "page": 0, "value": "1", "value_raw": "1"}, "unit-price": {"boxes": [{"boundingPoly": {"vertices": [{"x": 541, "y": 381}, {"x": 581, "y": 381}, {"x": 581, "y": 394}, {"x": 541, "y": 394}]}, "description": "100.00", "doc_line": 9, "line": 9, "page": 0}], "confidence": 0.9787451028823853, "page": 0, "value": "100.00", "value_raw": "100.00"}}, {"description": {"boxes": [{"boundingPoly": {"vertices": [{"x": 165, "y": 418}, {"x": 192, "y": 418}, {"x": 192, "y": 431}, {"x": 165, "y": 431}]}, "description": "New", "doc_line": 10, "line": 10, "page": 0}, {"boundingPoly": {"vertices": [{"x": 194, "y": 419}, {"x": 212, "y": 419}, {"x": 212, "y": 431}, {"x": 194, "y": 431}]}, "description": "set", "doc_line": 10, "line": 10, "page": 0}, {"boundingPoly": {"vertices": [{"x": 213, "y": 418}, {"x": 226, "y": 418}, {"x": 226, "y": 431}, {"x": 213, "y": 431}]}, "description": "of", "doc_line": 10, "line": 10, "page": 0}, {"boundingPoly": {"vertices": [{"x": 227, "y": 418}, {"x": 260, "y": 418}, {"x": 260, "y": 433}, {"x": 227, "y": 433}]}, "description": "pedal", "doc_line": 10, "line": 10, "page": 0}, {"boundingPoly": {"vertices": [{"x": 262, "y": 420}, {"x": 292, "y": 420}, {"x": 292, "y": 430}, {"x": 262, "y": 430}]}, "description": "arms", "doc_line": 10, "line": 10, "page": 0}], "confidence": 0.9804587364196777, "page": 0, "value": "New set of pedal arms", "value_raw": "New set of pedal arms"}, "item-po-no": {"boxes": [], "confidence": 0.0, "page": 0, "value": "", "value_raw": ""}, "line-amount": {"boxes": [{"boundingPoly": {"vertices": [{"x": 656, "y": 418}, {"x": 690, "y": 418}, {"x": 690, "y": 431}, {"x": 656, "y": 431}]}, "description": "30.00", "doc_line": 10, "line": 10, "page": 0}], "confidence": 0.9862556457519531, "page": 0, "value": "30.00", "value_raw": "30.00"}, "line-no": {"boxes": [], "confidence": 0.0, "page": 0, "value": "", "value_raw": ""}, "part-no": {"boxes": [], "confidence": 0.0, "page": 0, "value": "", "value_raw": ""}, "quantity": {"boxes": [{"boundingPoly": {"vertices": [{"x": 105, "y": 417}, {"x": 116, "y": 417}, {"x": 116, "y": 431}, {"x": 105, "y": 431}]}, "description": "2", "doc_line": 10, "line": 10, "page": 0}], "confidence": 0.7502382397651672, "page": 0, "value": "2", "value_raw": "2"}, "unit-price": {"boxes": [{"boundingPoly": {"vertices": [{"x": 548, "y": 418}, {"x": 581, "y": 418}, {"x": 581, "y": 431}, {"x": 548, "y": 431}]}, "description": "15.00", "doc_line": 10, "line": 10, "page": 0}], "confidence": 0.9765193462371826, "page": 0, "value": "15.00", "value_raw": "15.00"}}, {"description": {"boxes": [{"boundingPoly": {"vertices": [{"x": 165, "y": 455}, {"x": 199, "y": 455}, {"x": 199, "y": 468}, {"x": 165, "y": 468}]}, "description": "Labor", "doc_line": 11, "line": 11, "page": 0}, {"boundingPoly": {"vertices": [{"x": 200, "y": 455}, {"x": 227, "y": 455}, {"x": 227, "y": 468}, {"x": 200, "y": 468}]}, "description": "3hrs", "doc_line": 11, "line": 11, "page": 0}], "confidence": 0.9863256812095642, "page": 0, "value": "Labor 3hrs", "value_raw": "Labor 3hrs"}, "item-po-no": {"boxes": [], "confidence": 0.0, "page": 0, "value": "", "value_raw": ""}, "line-amount": {"boxes": [{"boundingPoly": {"vertices": [{"x": 657, "y": 455}, {"x": 689, "y": 455}, {"x": 689, "y": 468}, {"x": 657, "y": 468}]}, "description": "15.00", "doc_line": 11, "line": 11, "page": 0}], "confidence": 0.9727634191513062, "page": 0, "value": "15.00", "value_raw": "15.00"}, "line-no": {"boxes": [], "confidence": 0.0, "page": 0, "value": "", "value_raw": ""}, "part-no": {"boxes": [], "confidence": 0.0, "page": 0, "value": "", "value_raw": ""}, "quantity": {"boxes": [{"boundingPoly": {"vertices": [{"x": 105, "y": 455}, {"x": 115, "y": 455}, {"x": 115, "y": 468}, {"x": 105, "y": 468}]}, "description": "3", "doc_line": 11, "line": 11, "page": 0}], "confidence": 0.6970046162605286, "page": 0, "value": "3", "value_raw": "3"}, "unit-price": {"boxes": [{"boundingPoly": {"vertices": [{"x": 554, "y": 455}, {"x": 581, "y": 455}, {"x": 581, "y": 468}, {"x": 554, "y": 468}]}, "description": "5.00", "doc_line": 11, "line": 11, "page": 0}], "confidence": 0.8928316831588745, "page": 0, "value": "5.00", "value_raw": "5.00"}}], "name": {"boxes": [{"boundingPoly": {"vertices": [{"x": 99, "y": 76}, {"x": 142, "y": 76}, {"x": 142, "y": 95}, {"x": 99, "y": 95}]}, "description": "East", "doc_line": 0, "line": 0, "page": 0}, {"boundingPoly": {"vertices": [{"x": 145, "y": 76}, {"x": 206, "y": 76}, {"x": 206, "y": 98}, {"x": 145, "y": 98}]}, "description": "Repair", "doc_line": 0, "line": 0, "page": 0}, {"boundingPoly": {"vertices": [{"x": 210, "y": 77}, {"x": 243, "y": 77}, {"x": 243, "y": 95}, {"x": 210, "y": 95}]}, "description": "Inc.", "doc_line": 0, "line": 0, "page": 0}, {"boundingPoly": {"vertices": [{"x": 616, "y": 111}, {"x": 685, "y": 111}, {"x": 685, "y": 135}, {"x": 616, "y": 135}]}, "description": "LOGO", "doc_line": 1, "line": 1, "page": 0}], "confidence": 0.6215337514877319, "page": 0, "value": "East Repair Inc. LOGO", "value_raw": "East Repair Inc. LOGO"}, "net-amount": {"boxes": [{"boundingPoly": {"vertices": [{"x": 650, "y": 505}, {"x": 689, "y": 505}, {"x": 689, "y": 517}, {"x": 650, "y": 517}]}, "description": "145.00", "doc_line": 12, "line": 12, "page": 0}], "confidence": 0.9374870657920837, "page": 0, "value": "145.00", "value_raw": "145.00"}, "page_size": [[750, 1061]], "payment-addr": {"boxes": [], "confidence": 0.0, "page": 0, "value": "", "value_raw": ""}, "payment-terms": {"boxes": [{"boundingPoly": {"vertices": [{"x": 164, "y": 941}, {"x": 187, "y": 941}, {"x": 187, "y": 953}, {"x": 164, "y": 953}]}, "description": "due", "doc_line": 16, "line": 16, "page": 0}, {"boundingPoly": {"vertices": [{"x": 189, "y": 940}, {"x": 223, "y": 940}, {"x": 223, "y": 953}, {"x": 189, "y": 953}]}, "description": "within", "doc_line": 16, "line": 16, "page": 0}, {"boundingPoly": {"vertices": [{"x": 225, "y": 941}, {"x": 241, "y": 941}, {"x": 241, "y": 953}, {"x": 225, "y": 953}]}, "description": "15", "doc_line": 16, "line": 16, "page": 0}, {"boundingPoly": {"vertices": [{"x": 242, "y": 940}, {"x": 271, "y": 940}, {"x": 271, "y": 956}, {"x": 242, "y": 956}]}, "description": "days", "doc_line": 16, "line": 16, "page": 0}], "confidence": 0.6137503385543823, "page": 0, "value": "due within 15 days", "value_raw": "due within 15 days"}, "po-no": {"boxes": [{"boundingPoly": {"vertices": [{"x": 635, "y": 245}, {"x": 697, "y": 245}, {"x": 697, "y": 259}, {"x": 635, "y": 259}]}, "description": "2312/2019", "doc_line": 4, "line": 4, "page": 0}], "confidence": 0.7824729681015015, "page": 0, "value": "2312/2019", "value_raw": "2312/2019"}, "shipping-addr": {"boxes": [{"boundingPoly": {"vertices": [{"x": 302, "y": 246}, {"x": 332, "y": 246}, {"x": 332, "y": 259}, {"x": 302, "y": 259}]}, "description": "John", "doc_line": 4, "line": 4, "page": 0}, {"boundingPoly": {"vertices": [{"x": 334, "y": 246}, {"x": 368, "y": 246}, {"x": 368, "y": 259}, {"x": 334, "y": 259}]}, "description": "Smith", "doc_line": 4, "line": 4, "page": 0}, {"boundingPoly": {"vertices": [{"x": 303, "y": 264}, {"x": 332, "y": 264}, {"x": 332, "y": 277}, {"x": 303, "y": 277}]}, "description": "3787", "doc_line": 5, "line": 5, "page": 0}, {"boundingPoly": {"vertices": [{"x": 335, "y": 264}, {"x": 387, "y": 264}, {"x": 387, "y": 277}, {"x": 335, "y": 277}]}, "description": "Pineview", "doc_line": 5, "line": 5, "page": 0}, {"boundingPoly": {"vertices": [{"x": 388, "y": 264}, {"x": 420, "y": 264}, {"x": 420, "y": 277}, {"x": 388, "y": 277}]}, "description": "Drive", "doc_line": 5, "line": 5, "page": 0}, {"boundingPoly": {"vertices": [{"x": 303, "y": 282}, {"x": 369, "y": 282}, {"x": 369, "y": 297}, {"x": 303, "y": 297}]}, "description": "Cambridge,", "doc_line": 7, "line": 7, "page": 0}, {"boundingPoly": {"vertices": [{"x": 371, "y": 282}, {"x": 392, "y": 282}, {"x": 392, "y": 295}, {"x": 371, "y": 295}]}, "description": "MA", "doc_line": 7, "line": 7, "page": 0}, {"boundingPoly": {"vertices": [{"x": 394, "y": 283}, {"x": 431, "y": 283}, {"x": 431, "y": 295}, {"x": 394, "y": 295}]}, "description": "12210", "doc_line": 7, "line": 7, "page": 0}], "confidence": 0.9091944694519043, "page": 0, "value": "John Smith 3787 Pineview Drive Cambridge, MA 12210", "value_raw": "John Smith 3787 Pineview Drive Cambridge, MA 12210"}, "shipping-charges": {"boxes": [], "confidence": 0.0, "page": 0, "value": "", "value_raw": ""}, "tax": {"boxes": [{"boundingPoly": {"vertices": [{"x": 663, "y": 537}, {"x": 690, "y": 537}, {"x": 690, "y": 550}, {"x": 663, "y": 550}]}, "description": "9.06", "doc_line": 13, "line": 13, "page": 0}], "confidence": 0.9582584500312805, "page": 0, "value": "9.06", "value_raw": "9.06"}, "total": {"boxes": [{"boundingPoly": {"vertices": [{"x": 624, "y": 569}, {"x": 689, "y": 569}, {"x": 689, "y": 587}, {"x": 624, "y": 587}]}, "description": "$154.06", "doc_line": 14, "line": 14, "page": 0}], "confidence": 0.9799284338951111, "page": 0, "value": "154.06", "value_raw": "$154.06"}, "vendor-addr": {"boxes": [{"boundingPoly": {"vertices": [{"x": 99, "y": 116}, {"x": 129, "y": 116}, {"x": 129, "y": 129}, {"x": 99, "y": 129}]}, "description": "1912", "doc_line": 1, "line": 1, "page": 0}, {"boundingPoly": {"vertices": [{"x": 130, "y": 116}, {"x": 175, "y": 116}, {"x": 175, "y": 129}, {"x": 130, "y": 129}]}, "description": "Harvest", "doc_line": 1, "line": 1, "page": 0}, {"boundingPoly": {"vertices": [{"x": 177, "y": 116}, {"x": 207, "y": 116}, {"x": 207, "y": 129}, {"x": 177, "y": 129}]}, "description": "Lane", "doc_line": 1, "line": 1, "page": 0}, {"boundingPoly": {"vertices": [{"x": 98, "y": 134}, {"x": 126, "y": 134}, {"x": 126, "y": 147}, {"x": 98, "y": 147}]}, "description": "New", "doc_line": 2, "line": 2, "page": 0}, {"boundingPoly": {"vertices": [{"x": 127, "y": 134}, {"x": 158, "y": 134}, {"x": 158, "y": 148}, {"x": 127, "y": 148}]}, "description": "York,", "doc_line": 2, "line": 2, "page": 0}, {"boundingPoly": {"vertices": [{"x": 160, "y": 134}, {"x": 180, "y": 134}, {"x": 180, "y": 147}, {"x": 160, "y": 147}]}, "description": "NY", "doc_line": 2, "line": 2, "page": 0}, {"boundingPoly": {"vertices": [{"x": 181, "y": 135}, {"x": 218, "y": 135}, {"x": 218, "y": 147}, {"x": 181, "y": 147}]}, "description": "12210", "doc_line": 2, "line": 2, "page": 0}], "confidence": 0.9193394780158997, "page": 0, "value": "1912 Harvest Lane New York, NY 12210", "value_raw": "1912 Harvest Lane New York, NY 12210"}, "vendor-vat-no": {"boxes": [], "confidence": 0.0, "page": 0, "value": "", "value_raw": ""}}, "page_count": 1, "pages": [{"boxes": [[{"boundingPoly": {"vertices": [{"x": 99, "y": 76}, {"x": 142, "y": 76}, {"x": 142, "y": 95}, {"x": 99, "y": 95}]}, "confidence": 1.0, "description": "East"}, {"boundingPoly": {"vertices": [{"x": 145, "y": 76}, {"x": 206, "y": 76}, {"x": 206, "y": 98}, {"x": 145, "y": 98}]}, "confidence": 1.0, "description": "Repair"}, {"boundingPoly": {"vertices": [{"x": 210, "y": 77}, {"x": 243, "y": 77}, {"x": 243, "y": 95}, {"x": 210, "y": 95}]}, "confidence": 1.0, "description": "Inc."}], [{"boundingPoly": {"vertices": [{"x": 99, "y": 116}, {"x": 129, "y": 116}, {"x": 129, "y": 129}, {"x": 99, "y": 129}]}, "confidence": 1.0, "description": "1912"}, {"boundingPoly": {"vertices": [{"x": 130, "y": 116}, {"x": 175, "y": 116}, {"x": 175, "y": 129}, {"x": 130, "y": 129}]}, "confidence": 1.0, "description": "Harvest"}, {"boundingPoly": {"vertices": [{"x": 177, "y": 116}, {"x": 207, "y": 116}, {"x": 207, "y": 129}, {"x": 177, "y": 129}]}, "confidence": 1.0, "description": "Lane"}, {"boundingPoly": {"vertices": [{"x": 616, "y": 111}, {"x": 685, "y": 111}, {"x": 685, "y": 135}, {"x": 616, "y": 135}]}, "confidence": 1.0, "description": "LOGO"}], [{"boundingPoly": {"vertices": [{"x": 98, "y": 134}, {"x": 126, "y": 134}, {"x": 126, "y": 147}, {"x": 98, "y": 147}]}, "confidence": 1.0, "description": "New"}, {"boundingPoly": {"vertices": [{"x": 127, "y": 134}, {"x": 158, "y": 134}, {"x": 158, "y": 148}, {"x": 127, "y": 148}]}, "confidence": 1.0, "description": "York,"}, {"boundingPoly": {"vertices": [{"x": 160, "y": 134}, {"x": 180, "y": 134}, {"x": 180, "y": 147}, {"x": 160, "y": 147}]}, "confidence": 1.0, "description": "NY"}, {"boundingPoly": {"vertices": [{"x": 181, "y": 135}, {"x": 218, "y": 135}, {"x": 218, "y": 147}, {"x": 181, "y": 147}]}, "confidence": 1.0, "description": "12210"}], [{"boundingPoly": {"vertices": [{"x": 99, "y": 219}, {"x": 120, "y": 219}, {"x": 120, "y": 231}, {"x": 99, "y": 231}]}, "confidence": 0.98999995, "description": "Bill"}, {"boundingPoly": {"vertices": [{"x": 121, "y": 219}, {"x": 139, "y": 219}, {"x": 139, "y": 231}, {"x": 121, "y": 231}]}, "confidence": 0.98999995, "description": "To"}, {"boundingPoly": {"vertices": [{"x": 303, "y": 219}, {"x": 332, "y": 219}, {"x": 332, "y": 234}, {"x": 303, "y": 234}]}, "confidence": 0.98999995, "description": "Ship"}, {"boundingPoly": {"vertices": [{"x": 333, "y": 219}, {"x": 351, "y": 219}, {"x": 351, "y": 231}, {"x": 333, "y": 231}]}, "confidence": 1.0, "description": "To"}, {"boundingPoly": {"vertices": [{"x": 513, "y": 219}, {"x": 558, "y": 219}, {"x": 558, "y": 231}, {"x": 513, "y": 231}]}, "confidence": 1.0, "description": "Invoice"}, {"boundingPoly": {"vertices": [{"x": 560, "y": 219}, {"x": 589, "y": 219}, {"x": 589, "y": 231}, {"x": 560, "y": 231}]}, "confidence": 1.0, "description": "Date"}, {"boundingPoly": {"vertices": [{"x": 632, "y": 219}, {"x": 697, "y": 219}, {"x": 697, "y": 231}, {"x": 632, "y": 231}]}, "confidence": 1.0, "description": "11/02/2019"}], [{"boundingPoly": {"vertices": [{"x": 97, "y": 246}, {"x": 128, "y": 246}, {"x": 128, "y": 259}, {"x": 97, "y": 259}]}, "confidence": 1.0, "description": "John"}, {"boundingPoly": {"vertices": [{"x": 130, "y": 246}, {"x": 163, "y": 246}, {"x": 163, "y": 259}, {"x": 130, "y": 259}]}, "confidence": 1.0, "description": "Smith"}, {"boundingPoly": {"vertices": [{"x": 302, "y": 246}, {"x": 332, "y": 246}, {"x": 332, "y": 259}, {"x": 302, "y": 259}]}, "confidence": 1.0, "description": "John"}, {"boundingPoly": {"vertices": [{"x": 334, "y": 246}, {"x": 368, "y": 246}, {"x": 368, "y": 259}, {"x": 334, "y": 259}]}, "confidence": 1.0, "description": "Smith"}, {"boundingPoly": {"vertices": [{"x": 555, "y": 246}, {"x": 590, "y": 246}, {"x": 590, "y": 259}, {"x": 555, "y": 259}]}, "confidence": 1.0, "description": "P.O.#"}, {"boundingPoly": {"vertices": [{"x": 635, "y": 245}, {"x": 697, "y": 245}, {"x": 697, "y": 259}, {"x": 635, "y": 259}]}, "confidence": 1.0, "description": "2312/2019"}], [{"boundingPoly": {"vertices": [{"x": 98, "y": 264}, {"x": 108, "y": 264}, {"x": 108, "y": 277}, {"x": 98, "y": 277}]}, "confidence": 1.0, "description": "2"}, {"boundingPoly": {"vertices": [{"x": 109, "y": 264}, {"x": 142, "y": 264}, {"x": 142, "y": 277}, {"x": 109, "y": 277}]}, "confidence": 1.0, "description": "Court"}, {"boundingPoly": {"vertices": [{"x": 143, "y": 264}, {"x": 186, "y": 264}, {"x": 186, "y": 279}, {"x": 143, "y": 279}]}, "confidence": 1.0, "description": "Square"}, {"boundingPoly": {"vertices": [{"x": 303, "y": 264}, {"x": 332, "y": 264}, {"x": 332, "y": 277}, {"x": 303, "y": 277}]}, "confidence": 1.0, "description": "3787"}, {"boundingPoly": {"vertices": [{"x": 335, "y": 264}, {"x": 387, "y": 264}, {"x": 387, "y": 277}, {"x": 335, "y": 277}]}, "confidence": 1.0, "description": "Pineview"}, {"boundingPoly": {"vertices": [{"x": 388, "y": 264}, {"x": 420, "y": 264}, {"x": 420, "y": 277}, {"x": 388, "y": 277}]}, "confidence": 1.0, "description": "Drive"}], [{"boundingPoly": {"vertices": [{"x": 533, "y": 274}, {"x": 558, "y": 274}, {"x": 558, "y": 286}, {"x": 533, "y": 286}]}, "confidence": 1.0, "description": "Due"}, {"boundingPoly": {"vertices": [{"x": 560, "y": 273}, {"x": 589, "y": 273}, {"x": 589, "y": 286}, {"x": 560, "y": 286}]}, "confidence": 1.0, "description": "Date"}, {"boundingPoly": {"vertices": [{"x": 631, "y": 273}, {"x": 697, "y": 273}, {"x": 697, "y": 286}, {"x": 631, "y": 286}]}, "confidence": 1.0, "description": "26/02/2019"}], [{"boundingPoly": {"vertices": [{"x": 99, "y": 282}, {"x": 126, "y": 282}, {"x": 126, "y": 295}, {"x": 99, "y": 295}]}, "confidence": 1.0, "description": "New"}, {"boundingPoly": {"vertices": [{"x": 127, "y": 282}, {"x": 158, "y": 282}, {"x": 158, "y": 297}, {"x": 127, "y": 297}]}, "confidence": 0.98999995, "description": "York,"}, {"boundingPoly": {"vertices": [{"x": 160, "y": 282}, {"x": 180, "y": 282}, {"x": 180, "y": 295}, {"x": 160, "y": 295}]}, "confidence": 1.0, "description": "NY"}, {"boundingPoly": {"vertices": [{"x": 181, "y": 282}, {"x": 218, "y": 282}, {"x": 218, "y": 295}, {"x": 181, "y": 295}]}, "confidence": 1.0, "description": "12210"}, {"boundingPoly": {"vertices": [{"x": 303, "y": 282}, {"x": 369, "y": 282}, {"x": 369, "y": 297}, {"x": 303, "y": 297}]}, "confidence": 1.0, "description": "Cambridge,"}, {"boundingPoly": {"vertices": [{"x": 371, "y": 282}, {"x": 392, "y": 282}, {"x": 392, "y": 295}, {"x": 371, "y": 295}]}, "confidence": 1.0, "description": "MA"}, {"boundingPoly": {"vertices": [{"x": 394, "y": 283}, {"x": 431, "y": 283}, {"x": 431, "y": 295}, {"x": 394, "y": 295}]}, "confidence": 1.0, "description": "12210"}], [{"boundingPoly": {"vertices": [{"x": 118, "y": 348}, {"x": 141, "y": 348}, {"x": 141, "y": 364}, {"x": 118, "y": 364}]}, "confidence": 1.0, "description": "Qty"}, {"boundingPoly": {"vertices": [{"x": 283, "y": 348}, {"x": 353, "y": 348}, {"x": 353, "y": 364}, {"x": 283, "y": 364}]}, "confidence": 1.0, "description": "Description"}, {"boundingPoly": {"vertices": [{"x": 502, "y": 348}, {"x": 528, "y": 348}, {"x": 528, "y": 361}, {"x": 502, "y": 361}]}, "confidence": 1.0, "description": "Unit"}, {"boundingPoly": {"vertices": [{"x": 530, "y": 348}, {"x": 563, "y": 348}, {"x": 563, "y": 361}, {"x": 530, "y": 361}]}, "confidence": 1.0, "description": "Price"}, {"boundingPoly": {"vertices": [{"x": 614, "y": 349}, {"x": 664, "y": 349}, {"x": 664, "y": 362}, {"x": 614, "y": 362}]}, "confidence": 0.97999996, "description": "Amount"}], [{"boundingPoly": {"vertices": [{"x": 107, "y": 381}, {"x": 114, "y": 381}, {"x": 114, "y": 393}, {"x": 107, "y": 393}]}, "confidence": 1.0, "description": "1"}, {"boundingPoly": {"vertices": [{"x": 165, "y": 381}, {"x": 197, "y": 381}, {"x": 197, "y": 394}, {"x": 165, "y": 394}]}, "confidence": 1.0, "description": "Front"}, {"boundingPoly": {"vertices": [{"x": 198, "y": 382}, {"x": 220, "y": 382}, {"x": 220, "y": 394}, {"x": 198, "y": 394}]}, "confidence": 1.0, "description": "and"}, {"boundingPoly": {"vertices": [{"x": 222, "y": 383}, {"x": 247, "y": 383}, {"x": 247, "y": 394}, {"x": 222, "y": 394}]}, "confidence": 1.0, "description": "rear"}, {"boundingPoly": {"vertices": [{"x": 248, "y": 381}, {"x": 281, "y": 381}, {"x": 281, "y": 393}, {"x": 248, "y": 393}]}, "confidence": 1.0, "description": "brake"}, {"boundingPoly": {"vertices": [{"x": 283, "y": 381}, {"x": 321, "y": 381}, {"x": 321, "y": 394}, {"x": 283, "y": 394}]}, "confidence": 1.0, "description": "cables"}, {"boundingPoly": {"vertices": [{"x": 541, "y": 381}, {"x": 581, "y": 381}, {"x": 581, "y": 394}, {"x": 541, "y": 394}]}, "confidence": 1.0, "description": "100.00"}, {"boundingPoly": {"vertices": [{"x": 649, "y": 381}, {"x": 690, "y": 381}, {"x": 690, "y": 394}, {"x": 649, "y": 394}]}, "confidence": 1.0, "description": "100.00"}], [{"boundingPoly": {"vertices": [{"x": 105, "y": 417}, {"x": 116, "y": 417}, {"x": 116, "y": 431}, {"x": 105, "y": 431}]}, "confidence": 1.0, "description": "2"}, {"boundingPoly": {"vertices": [{"x": 165, "y": 418}, {"x": 192, "y": 418}, {"x": 192, "y": 431}, {"x": 165, "y": 431}]}, "confidence": 1.0, "description": "New"}, {"boundingPoly": {"vertices": [{"x": 194, "y": 419}, {"x": 212, "y": 419}, {"x": 212, "y": 431}, {"x": 194, "y": 431}]}, "confidence": 1.0, "description": "set"}, {"boundingPoly": {"vertices": [{"x": 213, "y": 418}, {"x": 226, "y": 418}, {"x": 226, "y": 431}, {"x": 213, "y": 431}]}, "confidence": 1.0, "description": "of"}, {"boundingPoly": {"vertices": [{"x": 227, "y": 418}, {"x": 260, "y": 418}, {"x": 260, "y": 433}, {"x": 227, "y": 433}]}, "confidence": 1.0, "description": "pedal"}, {"boundingPoly": {"vertices": [{"x": 262, "y": 420}, {"x": 292, "y": 420}, {"x": 292, "y": 430}, {"x": 262, "y": 430}]}, "confidence": 1.0, "description": "arms"}, {"boundingPoly": {"vertices": [{"x": 548, "y": 418}, {"x": 581, "y": 418}, {"x": 581, "y": 431}, {"x": 548, "y": 431}]}, "confidence": 1.0, "description": "15.00"}, {"boundingPoly": {"vertices": [{"x": 656, "y": 418}, {"x": 690, "y": 418}, {"x": 690, "y": 431}, {"x": 656, "y": 431}]}, "confidence": 1.0, "description": "30.00"}], [{"boundingPoly": {"vertices": [{"x": 105, "y": 455}, {"x": 115, "y": 455}, {"x": 115, "y": 468}, {"x": 105, "y": 468}]}, "confidence": 1.0, "description": "3"}, {"boundingPoly": {"vertices": [{"x": 165, "y": 455}, {"x": 199, "y": 455}, {"x": 199, "y": 468}, {"x": 165, "y": 468}]}, "confidence": 1.0, "description": "Labor"}, {"boundingPoly": {"vertices": [{"x": 200, "y": 455}, {"x": 227, "y": 455}, {"x": 227, "y": 468}, {"x": 200, "y": 468}]}, "confidence": 1.0, "description": "3hrs"}, {"boundingPoly": {"vertices": [{"x": 554, "y": 455}, {"x": 581, "y": 455}, {"x": 581, "y": 468}, {"x": 554, "y": 468}]}, "confidence": 1.0, "description": "5.00"}, {"boundingPoly": {"vertices": [{"x": 657, "y": 455}, {"x": 689, "y": 455}, {"x": 689, "y": 468}, {"x": 657, "y": 468}]}, "confidence": 1.0, "description": "15.00"}], [{"boundingPoly": {"vertices": [{"x": 478, "y": 504}, {"x": 526, "y": 504}, {"x": 526, "y": 517}, {"x": 478, "y": 517}]}, "confidence": 1.0, "description": "Subtotal"}, {"boundingPoly": {"vertices": [{"x": 650, "y": 505}, {"x": 689, "y": 505}, {"x": 689, "y": 517}, {"x": 650, "y": 517}]}, "confidence": 1.0, "description": "145.00"}], [{"boundingPoly": {"vertices": [{"x": 429, "y": 537}, {"x": 462, "y": 537}, {"x": 462, "y": 550}, {"x": 429, "y": 550}]}, "confidence": 1.0, "description": "Sales"}, {"boundingPoly": {"vertices": [{"x": 463, "y": 537}, {"x": 487, "y": 537}, {"x": 487, "y": 550}, {"x": 463, "y": 550}]}, "confidence": 1.0, "description": "Tax"}, {"boundingPoly": {"vertices": [{"x": 488, "y": 537}, {"x": 526, "y": 537}, {"x": 526, "y": 550}, {"x": 488, "y": 550}]}, "confidence": 1.0, "description": "6.25%"}, {"boundingPoly": {"vertices": [{"x": 663, "y": 537}, {"x": 690, "y": 537}, {"x": 690, "y": 550}, {"x": 663, "y": 550}]}, "confidence": 1.0, "description": "9.06"}], [{"boundingPoly": {"vertices": [{"x": 482, "y": 570}, {"x": 526, "y": 570}, {"x": 526, "y": 586}, {"x": 482, "y": 586}]}, "confidence": 0.98999995, "description": "Total"}, {"boundingPoly": {"vertices": [{"x": 624, "y": 569}, {"x": 689, "y": 569}, {"x": 689, "y": 587}, {"x": 624, "y": 587}]}, "confidence": 1.0, "description": "$154.06"}], [{"boundingPoly": {"vertices": [{"x": 98, "y": 901}, {"x": 138, "y": 901}, {"x": 138, "y": 913}, {"x": 98, "y": 913}]}, "confidence": 1.0, "description": "Terms"}, {"boundingPoly": {"vertices": [{"x": 140, "y": 901}, {"x": 151, "y": 901}, {"x": 151, "y": 913}, {"x": 140, "y": 913}]}, "confidence": 1.0, "description": "&"}, {"boundingPoly": {"vertices": [{"x": 152, "y": 901}, {"x": 220, "y": 901}, {"x": 220, "y": 913}, {"x": 152, "y": 913}]}, "confidence": 1.0, "description": "Conditions"}], [{"boundingPoly": {"vertices": [{"x": 99, "y": 941}, {"x": 150, "y": 941}, {"x": 150, "y": 956}, {"x": 99, "y": 956}]}, "confidence": 1.0, "description": "Payment"}, {"boundingPoly": {"vertices": [{"x": 152, "y": 940}, {"x": 163, "y": 940}, {"x": 163, "y": 953}, {"x": 152, "y": 953}]}, "confidence": 1.0, "description": "is"}, {"boundingPoly": {"vertices": [{"x": 164, "y": 941}, {"x": 187, "y": 941}, {"x": 187, "y": 953}, {"x": 164, "y": 953}]}, "confidence": 0.97999996, "description": "due"}, {"boundingPoly": {"vertices": [{"x": 189, "y": 940}, {"x": 223, "y": 940}, {"x": 223, "y": 953}, {"x": 189, "y": 953}]}, "confidence": 1.0, "description": "within"}, {"boundingPoly": {"vertices": [{"x": 225, "y": 941}, {"x": 241, "y": 941}, {"x": 241, "y": 953}, {"x": 225, "y": 953}]}, "confidence": 1.0, "description": "15"}, {"boundingPoly": {"vertices": [{"x": 242, "y": 940}, {"x": 271, "y": 940}, {"x": 271, "y": 956}, {"x": 242, "y": 956}]}, "confidence": 0.98999995, "description": "days"}], [{"boundingPoly": {"vertices": [{"x": 99, "y": 977}, {"x": 138, "y": 977}, {"x": 138, "y": 989}, {"x": 99, "y": 989}]}, "confidence": 1.0, "description": "Please"}, {"boundingPoly": {"vertices": [{"x": 140, "y": 977}, {"x": 174, "y": 977}, {"x": 174, "y": 989}, {"x": 140, "y": 989}]}, "confidence": 1.0, "description": "make"}, {"boundingPoly": {"vertices": [{"x": 175, "y": 977}, {"x": 216, "y": 977}, {"x": 216, "y": 990}, {"x": 175, "y": 990}]}, "confidence": 1.0, "description": "checks"}], [{"boundingPoly": {"vertices": [{"x": 218, "y": 977}, {"x": 264, "y": 977}, {"x": 264, "y": 992}, {"x": 218, "y": 992}]}, "confidence": 1.0, "description": "payable"}, {"boundingPoly": {"vertices": [{"x": 265, "y": 977}, {"x": 281, "y": 977}, {"x": 281, "y": 990}, {"x": 265, "y": 990}]}, "confidence": 1.0, "description": "to:"}, {"boundingPoly": {"vertices": [{"x": 283, "y": 977}, {"x": 310, "y": 977}, {"x": 310, "y": 990}, {"x": 283, "y": 990}]}, "confidence": 1.0, "description": "East"}, {"boundingPoly": {"vertices": [{"x": 311, "y": 977}, {"x": 351, "y": 977}, {"x": 351, "y": 992}, {"x": 311, "y": 992}]}, "confidence": 1.0, "description": "Repair"}, {"boundingPoly": {"vertices": [{"x": 352, "y": 977}, {"x": 374, "y": 977}, {"x": 374, "y": 990}, {"x": 352, "y": 990}]}, "confidence": 1.0, "description": "Inc."}]], "height": 1061, "page_rotation": 0, "width": 750}]}